setup.cfg
setup.py
bin/run_pipeline.py
dialectic_pipeline/__init__.py
dialectic_pipeline/apriori.py
dialectic_pipeline/featureExtraction.py
dialectic_pipeline/generateExplainer.py
dialectic_pipeline/lda.py
dialectic_pipeline/model_trainer.py
dialectic_pipeline/segmentation.py
dialectic_pipeline.egg-info/PKG-INFO
dialectic_pipeline.egg-info/SOURCES.txt
dialectic_pipeline.egg-info/dependency_links.txt
dialectic_pipeline.egg-info/requires.txt
dialectic_pipeline.egg-info/top_level.txt