Metadata-Version: 1.1
Name: dialectic-pipeline
Version: 0.2
Summary: Pipeline for augmenting text-fields with automatc, content-specific feedback to improve user generated text quality
Home-page: http://github.com/cudbg/Dialectic
Author: Hamed Nilforoshan
Author-email: hn2284@columbia.edu
License: MIT
Download-URL: https://github.com/cudbg/Dialectic/tarball/0.1
Platform: UNKNOWN
